yapygen/__init__.py
yapygen/__main__.py
yapygen/generate.py
yapygen/meta.py
yapygen/py.typed
yapygen/templates/.flake8
yapygen/templates/.gitignore
yapygen/templates/.pre-commit-config
yapygen/templates/MANIFEST.in
yapygen/templates/README
yapygen/templates/pyproject
yapygen/templates/licenses/MIT
yapygen-0.3.1.dist-info/LICENSE
yapygen-0.3.1.dist-info/METADATA
yapygen-0.3.1.dist-info/WHEEL
yapygen-0.3.1.dist-info/entry_points.txt
yapygen-0.3.1.dist-info/top_level.txt
yapygen-0.3.1.dist-info/RECORD
