Metadata-Version: 2.1
Name: yapygen
Version: 0.3.1
Summary: Yet Another Python Project Generator
Author-email: Qian <gokinjolno112358@gmail.com>
License: MIT License
Project-URL: Homepage, https://github.com/i1123581321/yapygen
Project-URL: Source, https://github.com/i1123581321/yapygen
Keywords: Project Generator,Interactive
Classifier: Programming Language :: Python :: 3
Classifier: Operating System :: OS Independent
Requires-Python: >=3.9
License-File: LICENSE
Requires-Dist: InquirerPy ~=0.3.4
Provides-Extra: dev
Requires-Dist: black ; extra == 'dev'
Requires-Dist: flake8 ; extra == 'dev'
Requires-Dist: isort ; extra == 'dev'
Requires-Dist: mypy ; extra == 'dev'
Requires-Dist: ipython ; extra == 'dev'
Requires-Dist: pre-commit ; extra == 'dev'
